{
  "header": {
    "title": "Canvas Editor"
  },
  "navigation": {
    "canvas": "Canvas",
    "gallery": "Gallery",
    "line": "Freehand",
    "eraser": "Eraser",
    "text": "Text",
    "export": "Export",
    "settings": "Settings"
  },
  "canvas": {
    "document": {
      "title": "Document",
      "name": {
        "label": "File name",
        "placeholder": "Enter name here"
      },
      "color": "Color"
    },
    "size": {
      "title": "Size",
      "width": "Width",
      "height": "Height"
    }
  },
  "gallery": {
    "title": "Upload",
    "choose": "Choose",
    "notFound": "No images found"
  },
  "line": {
    "title": "Pen",
    "size": "Size",
    "color": "Color"
  },
  "text": {
    "title": "Content",
    "input": {
      "label": "Text",
      "placeholder": "Enter text here",
      "button": "Add text"
    },
    "font": {
      "title": "Font",
      "size": "Size",
      "color": "Color"
    }
  },
  "export": {
    "title": "Format",
    "download": "Download",
    "image": "Image",
    "jpg": "JPG",
    "png": "PNG",
    "pdf": "PDF"
  },
  "settings": {
    "title": "Settings",
    "language": {
      "label": "Language",
      "options": {
        "en": "English",
        "nl": "Dutch"
      }
    },
    "theme": {
      "label": "Theme",
      "options": {
        "light": "Light",
        "dark": "Dark"
      }
    },
    "size": {
      "label": "Size",
      "options": {
        "sm": "Small",
        "md": "Medium",
        "lg": "Large"
      }
    }
  },
  "overview": {
    "zoom": {
      "label": "Zoom",
      "options": {
        "25": "25%",
        "50": "50%",
        "100": "100%",
        "150": "150%",
        "200": "200%"
      }
    }
  }
}
